testDanXvo/__init__.py
testDanXvo-0.1.0.dist-info/METADATA
testDanXvo-0.1.0.dist-info/WHEEL
testDanXvo-0.1.0.dist-info/entry_points.txt
testDanXvo-0.1.0.dist-info/top_level.txt
testDanXvo-0.1.0.dist-info/RECORD
