Metadata-Version: 2.1
Name: testDanXvo
Version: 0.1.0
Requires-Dist: requests
Requires-Dist: numpy
